md_index/__init__.py
md_index/cli.py
md_index/index.py
md_index-0.1.1.dist-info/entry_points.txt
md_index-0.1.1.dist-info/LICENSE
md_index-0.1.1.dist-info/METADATA
md_index-0.1.1.dist-info/WHEEL
md_index-0.1.1.dist-info/RECORD
