Metadata-Version: 2.1
Name: md-index
Version: 0.1.1
Summary: Generate markdown index of files in folder for mkdocs.
License: MIT
Author: mobyw
Author-email: mobyw66@gmail.com
Requires-Python: >=3.7,<4.0
Classifier: License :: OSI Approved :: MIT License
Classifier: Programming Language :: Python :: 3
Classifier: Programming Language :: Python :: 3.7
Classifier: Programming Language :: Python :: 3.8
Classifier: Programming Language :: Python :: 3.9
Classifier: Programming Language :: Python :: 3.10
Classifier: Programming Language :: Python :: 3.11
Requires-Dist: click (>=8.1.3,<9.0.0)
